{"cameraMode":{"drawMode":1,"name":"Wireframe","section":"Shading Mode"},"sceneLighting":true,"audioPlay":false,"sceneViewState":{"m_AlwaysRefresh":false,"showFog":true,"showSkybox":true,"showFlares":true,"showImageEffects":true,"showParticleSystems":true,"showVisualEffectGraphs":true,"m_FxEnabled":true},"in2DMode":false,"pivot":{"x":-7.592868328094482,"y":2.6505234241485597,"z":0.10640668869018555},"rotation":{"x":-0.053867824375629428,"y":-0.9056583642959595,"z":0.4028189480304718,"w":-0.12104474753141403},"size":8.48061466217041,"orthographic":false}